DiggersToolbox-0.1.0.dist-info/METADATA
DiggersToolbox-0.1.0.dist-info/RECORD
DiggersToolbox-0.1.0.dist-info/WHEEL
DiggersToolbox-0.1.0.dist-info/entry_points.txt
DiggersToolbox-0.1.0.dist-info/top_level.txt
diggers_toolbox/__init__.py
diggers_toolbox/__main__.py
diggers_toolbox/conversion.py
diggers_toolbox/utils.py
diggers_toolbox/cli/__init__.py
diggers_toolbox/cli/conversion.py
diggers_toolbox/cli/utils.py
